gitra/__init__.py
gitra/_version.py
gitra-0.0.1.dist-info/METADATA
gitra-0.0.1.dist-info/WHEEL
gitra-0.0.1.dist-info/licenses/LICENSE
gitra-0.0.1.dist-info/RECORD
