Metadata-Version: 2.4
Name: gitra
Version: 0.0.1
Author-email: "kris.wang" <wenhom.wang@gmail.com>
License-Expression: MIT
License-File: LICENSE
Requires-Python: >=3.10
Provides-Extra: dev
Requires-Dist: rich>=14.2.0; extra == 'dev'
Requires-Dist: rtoml>=0.12.0; extra == 'dev'
